{
  "https://almedia.blob.core.windows.net/audio/lZZiE-EofAE.mp3": {
    "guid": "lZZiE-EofAE",
    "duration": 1181,
    "type": "audio/mpeg",
    "size": 18893361
  },
  "https://almedia.blob.core.windows.net/audio/N3x9BQi9G7E.mp3": {
    "guid": "N3x9BQi9G7E",
    "duration": 2300,
    "type": "audio/mpeg",
    "size": 36799150
  },
  "https://almedia.blob.core.windows.net/audio/QoqSU8zZUSg.mp3": {
    "guid": "QoqSU8zZUSg",
    "duration": 1333,
    "type": "audio/mpeg",
    "size": 21327555
  },
  "https://almedia.blob.core.windows.net/audio/teUXh0wcU64.mp3": {
    "guid": "teUXh0wcU64",
    "duration": 981,
    "type": "audio/mpeg",
    "size": 15689703
  },
  "https://almedia.blob.core.windows.net/audio/JDN7PcroYBA.mp3": {
    "guid": "JDN7PcroYBA",
    "duration": 1026,
    "type": "audio/mpeg",
    "size": 16402324
  },
  "https://almedia.blob.core.windows.net/audio/C87bdxRW14w.mp3": {
    "guid": "C87bdxRW14w",
    "duration": 2896,
    "type": "audio/mpeg",
    "size": 46336978
  },
  "https://almedia.blob.core.windows.net/audio/JzQeoiJCXIo.mp3": {
    "guid": "JzQeoiJCXIo",
    "duration": 2539,
    "type": "audio/mpeg",
    "size": 40611356
  },
  "https://almedia.blob.core.windows.net/audio/UTfPX-sPcgA.mp3": {
    "guid": "UTfPX-sPcgA",
    "duration": 1560,
    "type": "audio/mpeg",
    "size": 24955858
  },
  "https://almedia.blob.core.windows.net/audio/k5E7O4tiCAs.mp3": {
    "guid": "k5E7O4tiCAs",
    "duration": 1599,
    "type": "audio/mpeg",
    "size": 25572766
  },
  "https://almedia.blob.core.windows.net/audio/KjprZsPDgV8.mp3": {
    "guid": "KjprZsPDgV8",
    "duration": 753,
    "type": "audio/mpeg",
    "size": 6025207
  },
  "https://almedia.blob.core.windows.net/audio/qCaNGN48y0Y.mp3": {
    "guid": "qCaNGN48y0Y",
    "duration": 1015,
    "type": "audio/mpeg",
    "size": 16234304
  },
  "https://almedia.blob.core.windows.net/audio/d_XxojTTYaM.mp3": {
    "guid": "d_XxojTTYaM",
    "duration": 1429,
    "type": "audio/mpeg",
    "size": 22848926
  },
  "https://almedia.blob.core.windows.net/audio/-Xeo6gv0kbA.mp3": {
    "guid": "-Xeo6gv0kbA",
    "duration": 1435,
    "type": "audio/mpeg",
    "size": 17222542
  },
  "https://almedia.blob.core.windows.net/audio/gLWtY8_8b4k.mp3": {
    "guid": "gLWtY8_8b4k",
    "duration": 1445,
    "type": "audio/mpeg",
    "size": 23105553
  },
  "https://almedia.blob.core.windows.net/audio/qsMLDb7FIJ4.mp3": {
    "guid": "qsMLDb7FIJ4",
    "duration": 3305,
    "type": "audio/mpeg",
    "size": 52870934
  },
  "https://almedia.blob.core.windows.net/audio/mM4NAojkukk.mp3": {
    "guid": "mM4NAojkukk",
    "duration": 1760,
    "type": "audio/mpeg",
    "size": 28158680
  },
  "https://almedia.blob.core.windows.net/audio/tG4qiQyqAqE.mp3": {
    "guid": "tG4qiQyqAqE",
    "duration": 1261,
    "type": "audio/mpeg",
    "size": 20166464
  },
  "https://almedia.blob.core.windows.net/audio/O8e7R8UmcH0.mp3": {
    "guid": "O8e7R8UmcH0",
    "duration": 1268,
    "type": "audio/mpeg",
    "size": 20286418
  },
  "https://almedia.blob.core.windows.net/audio/QLEB3QY0H9A.mp3": {
    "guid": "QLEB3QY0H9A",
    "duration": 1595,
    "type": "audio/mpeg",
    "size": 25516342
  },
  "https://almedia.blob.core.windows.net/audio/F1wtNLFQ64I.mp3": {
    "guid": "F1wtNLFQ64I",
    "duration": 1802,
    "type": "audio/mpeg",
    "size": 28831176
  },
  "https://almedia.blob.core.windows.net/audio/32Te58QV1ZU.mp3": {
    "guid": "32Te58QV1ZU",
    "duration": 2200,
    "type": "audio/mpeg",
    "size": 35189589
  },
  "https://almedia.blob.core.windows.net/audio/NK-4q4FzeNM.mp3": {
    "guid": "NK-4q4FzeNM",
    "duration": 1681,
    "type": "audio/mpeg",
    "size": 26882232
  },
  "https://almedia.blob.core.windows.net/audio/jb2qMmRpC4c.mp3": {
    "guid": "jb2qMmRpC4c",
    "duration": 1571,
    "type": "audio/mpeg",
    "size": 25131819
  },
  "https://almedia.blob.core.windows.net/audio/jeVtge9TpX8.mp3": {
    "guid": "jeVtge9TpX8",
    "duration": 1507,
    "type": "audio/mpeg",
    "size": 24098624
  },
  "https://almedia.blob.core.windows.net/audio/CsmLe1toP6k.mp3": {
    "guid": "CsmLe1toP6k",
    "duration": 2090,
    "type": "audio/mpeg",
    "size": 33435414
  },
  "https://almedia.blob.core.windows.net/audio/3HNmXjZhkmI.mp3": {
    "guid": "3HNmXjZhkmI",
    "duration": 2800,
    "type": "audio/mpeg",
    "size": 44799307
  },
  "https://almedia.blob.core.windows.net/audio/68Zp1ZyTOAQ.mp3": {
    "guid": "68Zp1ZyTOAQ",
    "duration": 2707,
    "type": "audio/mpeg",
    "size": 43308028
  },
  "https://almedia.blob.core.windows.net/audio/gNrfJYg0xHo.mp3": {
    "guid": "gNrfJYg0xHo",
    "duration": 2136,
    "type": "audio/mpeg",
    "size": 34162245
  },
  "https://almedia.blob.core.windows.net/audio/Nf0h9zUwzcQ.mp3": {
    "guid": "Nf0h9zUwzcQ",
    "duration": 1492,
    "type": "audio/mpeg",
    "size": 23857880
  },
  "https://almedia.blob.core.windows.net/audio/DTPuY4QbU8Y.mp3": {
    "guid": "DTPuY4QbU8Y",
    "duration": 1613,
    "type": "audio/mpeg",
    "size": 25795538
  },
  "https://almedia.blob.core.windows.net/audio/cEOWbNN5CBA.mp3": {
    "guid": "cEOWbNN5CBA",
    "duration": 1839,
    "type": "audio/mpeg",
    "size": 29425096
  },
  "https://almedia.blob.core.windows.net/audio/YJtQ7Ot8UpY.mp3": {
    "guid": "YJtQ7Ot8UpY",
    "duration": 1262,
    "type": "audio/mpeg",
    "size": 20175241
  },
  "https://almedia.blob.core.windows.net/audio/rsFxg1N0Bgc.mp3": {
    "guid": "rsFxg1N0Bgc",
    "duration": 1788,
    "type": "audio/mpeg",
    "size": 28592103
  },
  "https://almedia.blob.core.windows.net/audio/k1NDCKyM91I.mp3": {
    "guid": "k1NDCKyM91I",
    "duration": 2385,
    "type": "audio/mpeg",
    "size": 38145396
  },
  "https://almedia.blob.core.windows.net/audio/gD6KwPjzO9g.mp3": {
    "guid": "gD6KwPjzO9g",
    "duration": 3151,
    "type": "audio/mpeg",
    "size": 50413334
  },
  "https://almedia.blob.core.windows.net/audio/N-rGGBxrZy4.mp3": {
    "guid": "N-rGGBxrZy4",
    "duration": 4045,
    "type": "audio/mpeg",
    "size": 64720495
  },
  "https://almedia.blob.core.windows.net/audio/epXN2H1SenI.mp3": {
    "guid": "epXN2H1SenI",
    "duration": 2715,
    "type": "audio/mpeg",
    "size": 43438432
  },
  "https://almedia.blob.core.windows.net/audio/5GNgnJy9xNk.mp3": {
    "guid": "5GNgnJy9xNk",
    "duration": 3019,
    "type": "audio/mpeg",
    "size": 48291774
  },
  "https://almedia.blob.core.windows.net/audio/0dTWnFxSUHM.mp3": {
    "guid": "0dTWnFxSUHM",
    "duration": 5120,
    "type": "audio/mpeg",
    "size": 81918262
  },
  "https://almedia.blob.core.windows.net/audio/dgvShGoxndE.mp3": {
    "guid": "dgvShGoxndE",
    "duration": 3340,
    "type": "audio/mpeg",
    "size": 53425984
  },
  "https://almedia.blob.core.windows.net/audio/AWStPfevc3Q.mp3": {
    "guid": "AWStPfevc3Q",
    "duration": 2889,
    "type": "audio/mpeg",
    "size": 46225383
  },
  "https://almedia.blob.core.windows.net/audio/7NigWO-v3_0.mp3": {
    "guid": "7NigWO-v3_0",
    "duration": 1697,
    "type": "audio/mpeg",
    "size": 27142203
  },
  "https://almedia.blob.core.windows.net/audio/pIluLqVYO3w.mp3": {
    "guid": "pIluLqVYO3w",
    "duration": 2232,
    "type": "audio/mpeg",
    "size": 35711202
  },
  "https://almedia.blob.core.windows.net/audio/EQoxhhzStAU.mp3": {
    "guid": "EQoxhhzStAU",
    "duration": 2082,
    "type": "audio/mpeg",
    "size": 33300414
  },
  "https://almedia.blob.core.windows.net/audio/fKIOkx1mmos.mp3": {
    "guid": "fKIOkx1mmos",
    "duration": 1350,
    "type": "audio/mpeg",
    "size": 21600900
  },
  "https://almedia.blob.core.windows.net/audio/Cmiu8l1egUg.mp3": {
    "guid": "Cmiu8l1egUg",
    "duration": 1078,
    "type": "audio/mpeg",
    "size": 17236570
  },
  "https://almedia.blob.core.windows.net/audio/iM7Q8mWttrU.mp3": {
    "guid": "iM7Q8mWttrU",
    "duration": 1120,
    "type": "audio/mpeg",
    "size": 17917008
  },
  "https://almedia.blob.core.windows.net/audio/eM-8DgJFiK0.mp3": {
    "guid": "eM-8DgJFiK0",
    "duration": 848,
    "type": "audio/mpeg",
    "size": 13568978
  },
  "https://almedia.blob.core.windows.net/audio/i2UwB-l6CGM.mp3": {
    "guid": "i2UwB-l6CGM",
    "duration": 1207,
    "type": "audio/mpeg",
    "size": 19310484
  },
  "https://almedia.blob.core.windows.net/audio/V8_eFIh6ASw.mp3": {
    "guid": "V8_eFIh6ASw",
    "duration": 1652,
    "type": "audio/mpeg",
    "size": 26420805
  },
  "https://almedia.blob.core.windows.net/audio/yaGXA3vdEvw.mp3": {
    "guid": "yaGXA3vdEvw",
    "duration": 1547,
    "type": "audio/mpeg",
    "size": 24747297
  },
  "https://almedia.blob.core.windows.net/audio/oOsGOdP9pjM.mp3": {
    "guid": "oOsGOdP9pjM",
    "duration": 1340,
    "type": "audio/mpeg",
    "size": 21432045
  },
  "https://almedia.blob.core.windows.net/audio/vMDuNWZBXxM.mp3": {
    "guid": "vMDuNWZBXxM",
    "duration": 1879,
    "type": "audio/mpeg",
    "size": 30064992
  },
  "https://almedia.blob.core.windows.net/audio/axWW8qWjiRQ.mp3": {
    "guid": "axWW8qWjiRQ",
    "duration": 1853,
    "type": "audio/mpeg",
    "size": 29648286
  },
  "https://almedia.blob.core.windows.net/audio/2pgZDa6vq-w.mp3": {
    "guid": "2pgZDa6vq-w",
    "duration": 1939,
    "type": "audio/mpeg",
    "size": 31009579
  },
  "https://almedia.blob.core.windows.net/audio/BN8c_uOYzHA.mp3": {
    "guid": "BN8c_uOYzHA",
    "duration": 1414,
    "type": "audio/mpeg",
    "size": 22609436
  },
  "https://almedia.blob.core.windows.net/audio/MvpmKbbUjP4.mp3": {
    "guid": "MvpmKbbUjP4",
    "duration": 1500,
    "type": "audio/mpeg",
    "size": 23986611
  },
  "https://almedia.blob.core.windows.net/audio/UD-iWHfq-hY.mp3": {
    "guid": "UD-iWHfq-hY",
    "duration": 1527,
    "type": "audio/mpeg",
    "size": 24427140
  },
  "https://almedia.blob.core.windows.net/audio/RXsoIIBeTh0.mp3": {
    "guid": "RXsoIIBeTh0",
    "duration": 1431,
    "type": "audio/mpeg",
    "size": 22889886
  },
  "https://almedia.blob.core.windows.net/audio/7sRqd-nKbLI.mp3": {
    "guid": "7sRqd-nKbLI",
    "duration": 1147,
    "type": "audio/mpeg",
    "size": 18350432
  },
  "https://almedia.blob.core.windows.net/audio/mq-wdHqs9RY.mp3": {
    "guid": "mq-wdHqs9RY",
    "duration": 1127,
    "type": "audio/mpeg",
    "size": 18029021
  },
  "https://almedia.blob.core.windows.net/audio/6YLMomQQLA0.mp3": {
    "guid": "6YLMomQQLA0",
    "duration": 2212,
    "type": "audio/mpeg",
    "size": 35382686
  },
  "https://almedia.blob.core.windows.net/audio/SGD2xas1uuU.mp3": {
    "guid": "SGD2xas1uuU",
    "duration": 1966,
    "type": "audio/mpeg",
    "size": 31443003
  },
  "https://almedia.blob.core.windows.net/audio/x1hOksr-8x0.mp3": {
    "guid": "x1hOksr-8x0",
    "duration": 916,
    "type": "audio/mpeg",
    "size": 14642298
  },
  "https://almedia.blob.core.windows.net/audio/lAD-SF9ls2Y.mp3": {
    "guid": "lAD-SF9ls2Y",
    "duration": 1067,
    "type": "audio/mpeg",
    "size": 17068133
  },
  "https://almedia.blob.core.windows.net/audio/AiM4B33_m20.mp3": {
    "guid": "AiM4B33_m20",
    "duration": 1340,
    "type": "audio/mpeg",
    "size": 21440822
  },
  "https://almedia.blob.core.windows.net/audio/h0OyNmS39Bc.mp3": {
    "guid": "h0OyNmS39Bc",
    "duration": 1307,
    "type": "audio/mpeg",
    "size": 20904162
  },
  "https://almedia.blob.core.windows.net/audio/OAzvFWGKj18.mp3": {
    "guid": "OAzvFWGKj18",
    "duration": 1169,
    "type": "audio/mpeg",
    "size": 18702353
  },
  "https://almedia.blob.core.windows.net/audio/lZ0_5_Klnco.mp3": {
    "guid": "lZ0_5_Klnco",
    "duration": 1363,
    "type": "audio/mpeg",
    "size": 21809044
  },
  "https://almedia.blob.core.windows.net/audio/NCmYTulIdxw.mp3": {
    "guid": "NCmYTulIdxw",
    "duration": 1265,
    "type": "audio/mpeg",
    "size": 20240025
  },
  "https://almedia.blob.core.windows.net/audio/M05X8OG6tX0.mp3": {
    "guid": "M05X8OG6tX0",
    "duration": 1383,
    "type": "audio/mpeg",
    "size": 22121677
  },
  "https://almedia.blob.core.windows.net/audio/btdYHpJHBLM.mp3": {
    "guid": "btdYHpJHBLM",
    "duration": 1787,
    "type": "audio/mpeg",
    "size": 28592103
  },
  "https://almedia.blob.core.windows.net/audio/XWjWtnHS3cM.mp3": {
    "guid": "XWjWtnHS3cM",
    "duration": 1302,
    "type": "audio/mpeg",
    "size": 20823914
  },
  "https://almedia.blob.core.windows.net/audio/U-KmNDb_3sc.mp3": {
    "guid": "U-KmNDb_3sc",
    "duration": 1384,
    "type": "audio/mpeg",
    "size": 22137142
  },
  "https://almedia.blob.core.windows.net/audio/GuDgxyHifAs.mp3": {
    "guid": "GuDgxyHifAs",
    "duration": 1877,
    "type": "audio/mpeg",
    "size": 30017344
  },
  "https://almedia.blob.core.windows.net/audio/QGxmK_FKROI.mp3": {
    "guid": "QGxmK_FKROI",
    "duration": 1473,
    "type": "audio/mpeg",
    "size": 23554859
  },
  "https://almedia.blob.core.windows.net/audio/M9ebC4xQmlg.mp3": {
    "guid": "M9ebC4xQmlg",
    "duration": 1515,
    "type": "audio/mpeg",
    "size": 24227774
  },
  "https://almedia.blob.core.windows.net/audio/zaOheE_9SeY.mp3": {
    "guid": "zaOheE_9SeY",
    "duration": 1181,
    "type": "audio/mpeg",
    "size": 18886673
  },
  "https://almedia.blob.core.windows.net/audio/xhHX2myo2bs.mp3": {
    "guid": "xhHX2myo2bs",
    "duration": 1714,
    "type": "audio/mpeg",
    "size": 27415130
  },
  "https://almedia.blob.core.windows.net/audio/5IygFPYpuF0.mp3": {
    "guid": "5IygFPYpuF0",
    "duration": 3176,
    "type": "audio/mpeg",
    "size": 50814575
  },
  "https://almedia.blob.core.windows.net/audio/nHxTAykHXMY.mp3": {
    "guid": "nHxTAykHXMY",
    "duration": 2251,
    "type": "audio/mpeg",
    "size": 36007117
  },
  "https://almedia.blob.core.windows.net/audio/DJjssr-IDzg.mp3": {
    "guid": "DJjssr-IDzg",
    "duration": 2133,
    "type": "audio/mpeg",
    "size": 34117524
  },
  "https://almedia.blob.core.windows.net/audio/7HEy1jOpOpg.mp3": {
    "guid": "7HEy1jOpOpg",
    "duration": 1353,
    "type": "audio/mpeg",
    "size": 21641024
  },
  "https://almedia.blob.core.windows.net/audio/Xf_d_fMj5IM.mp3": {
    "guid": "Xf_d_fMj5IM",
    "duration": 1267,
    "type": "audio/mpeg",
    "size": 20271372
  },
  "https://almedia.blob.core.windows.net/audio/U6QS5oCZj-w.mp3": {
    "guid": "U6QS5oCZj-w",
    "duration": 1186,
    "type": "audio/mpeg",
    "size": 18973191
  },
  "https://almedia.blob.core.windows.net/audio/IpoAuasmOSA.mp3": {
    "guid": "IpoAuasmOSA",
    "duration": 1135,
    "type": "audio/mpeg",
    "size": 18149393
  },
  "https://almedia.blob.core.windows.net/audio/bAM1vof7XsY.mp3": {
    "guid": "bAM1vof7XsY",
    "duration": 1880,
    "type": "audio/mpeg",
    "size": 30080456
  },
  "https://almedia.blob.core.windows.net/audio/eUvH4MEZG_I.mp3": {
    "guid": "eUvH4MEZG_I",
    "duration": 2825,
    "type": "audio/mpeg",
    "size": 45199712
  },
  "https://almedia.blob.core.windows.net/audio/lyPXSS-FNQ8.mp3": {
    "guid": "lyPXSS-FNQ8",
    "duration": 1163,
    "type": "audio/mpeg",
    "size": 18597027
  },
  "https://almedia.blob.core.windows.net/audio/ilkfVaF6H2I.mp3": {
    "guid": "ilkfVaF6H2I",
    "duration": 1821,
    "type": "audio/mpeg",
    "size": 29136286
  },
  "https://almedia.blob.core.windows.net/audio/atTEs7Lj-ig.mp3": {
    "guid": "atTEs7Lj-ig",
    "duration": 2505,
    "type": "audio/mpeg",
    "size": 40075114
  },
  "https://almedia.blob.core.windows.net/audio/zZjvhMmKvfw.mp3": {
    "guid": "zZjvhMmKvfw",
    "duration": 1436,
    "type": "audio/mpeg",
    "size": 22969716
  },
  "https://almedia.blob.core.windows.net/audio/egbCxzFCOJE.mp3": {
    "guid": "egbCxzFCOJE",
    "duration": 960,
    "type": "audio/mpeg",
    "size": 15354082
  },
  "https://almedia.blob.core.windows.net/audio/b269e2tiUt4.mp3": {
    "guid": "b269e2tiUt4",
    "duration": 2587,
    "type": "audio/mpeg",
    "size": 41380818
  },
  "https://almedia.blob.core.windows.net/audio/lYqrpeKokmM.mp3": {
    "guid": "lYqrpeKokmM",
    "duration": 1389,
    "type": "audio/mpeg",
    "size": 22216972
  },
  "https://almedia.blob.core.windows.net/audio/1WbUh8iEkFE.mp3": {
    "guid": "1WbUh8iEkFE",
    "duration": 1762,
    "type": "audio/mpeg",
    "size": 28191698
  },
  "https://almedia.blob.core.windows.net/audio/uQEsZw-QWdg.mp3": {
    "guid": "uQEsZw-QWdg",
    "duration": 1829,
    "type": "audio/mpeg",
    "size": 29264600
  },
  "https://almedia.blob.core.windows.net/audio/LkVoZkJ12LU.mp3": {
    "guid": "LkVoZkJ12LU",
    "duration": 887,
    "type": "audio/mpeg",
    "size": 14177527
  },
  "https://almedia.blob.core.windows.net/audio/y1pe0P7M8Jo.mp3": {
    "guid": "y1pe0P7M8Jo",
    "duration": 1699,
    "type": "audio/mpeg",
    "size": 27174386
  },
  "https://almedia.blob.core.windows.net/audio/3IDGh_DG8h8.mp3": {
    "guid": "3IDGh_DG8h8",
    "duration": 1492,
    "type": "audio/mpeg",
    "size": 23867075
  },
  "https://almedia.blob.core.windows.net/audio/9eGok24WP5I.mp3": {
    "guid": "9eGok24WP5I",
    "duration": 1878,
    "type": "audio/mpeg",
    "size": 30041168
  },
  "https://almedia.blob.core.windows.net/audio/Mn8Vwy0ak7I.mp3": {
    "guid": "Mn8Vwy0ak7I",
    "duration": 1322,
    "type": "audio/mpeg",
    "size": 21152430
  },
  "https://almedia.blob.core.windows.net/audio/1519DquE7k4.mp3": {
    "guid": "1519DquE7k4",
    "duration": 1094,
    "type": "audio/mpeg",
    "size": 17500721
  },
  "https://almedia.blob.core.windows.net/audio/QiwMZijoGno.mp3": {
    "guid": "QiwMZijoGno",
    "duration": 1759,
    "type": "audio/mpeg",
    "size": 28143633
  },
  "https://almedia.blob.core.windows.net/audio/PCf6HnKQqcE.mp3": {
    "guid": "PCf6HnKQqcE",
    "duration": 1450,
    "type": "audio/mpeg",
    "size": 23194161
  },
  "https://almedia.blob.core.windows.net/audio/lECPyAjSuGs.mp3": {
    "guid": "lECPyAjSuGs",
    "duration": 1097,
    "type": "audio/mpeg",
    "size": 17540427
  },
  "https://almedia.blob.core.windows.net/audio/dNG-zx7X8Es.mp3": {
    "guid": "dNG-zx7X8Es",
    "duration": 691,
    "type": "audio/mpeg",
    "size": 11054118
  },
  "https://almedia.blob.core.windows.net/audio/NmRNnwf4GX4.mp3": {
    "guid": "NmRNnwf4GX4",
    "duration": 982,
    "type": "audio/mpeg",
    "size": 15698481
  },
  "https://almedia.blob.core.windows.net/audio/UGov0C7lSbQ.mp3": {
    "guid": "UGov0C7lSbQ",
    "duration": 1447,
    "type": "audio/mpeg",
    "size": 23138154
  },
  "https://almedia.blob.core.windows.net/audio/KLC9rvvTU10.mp3": {
    "guid": "KLC9rvvTU10",
    "duration": 1235,
    "type": "audio/mpeg",
    "size": 19750595
  },
  "https://almedia.blob.core.windows.net/audio/wLb6LrjmcGo.mp3": {
    "guid": "wLb6LrjmcGo",
    "duration": 1222,
    "type": "audio/mpeg",
    "size": 19550810
  },
  "https://almedia.blob.core.windows.net/audio/EtyDRiHmDws.mp3": {
    "guid": "EtyDRiHmDws",
    "duration": 2189,
    "type": "audio/mpeg",
    "size": 35022405
  },
  "https://almedia.blob.core.windows.net/audio/9tq_72lT0Ro.mp3": {
    "guid": "9tq_72lT0Ro",
    "duration": 1907,
    "type": "audio/mpeg",
    "size": 30497997
  },
  "https://almedia.blob.core.windows.net/audio/hzGnCFvPsnU.mp3": {
    "guid": "hzGnCFvPsnU",
    "duration": 1682,
    "type": "audio/mpeg",
    "size": 26910236
  },
  "https://almedia.blob.core.windows.net/audio/x6kEEZjZpdI.mp3": {
    "guid": "x6kEEZjZpdI",
    "duration": 1489,
    "type": "audio/mpeg",
    "size": 23810650
  },
  "https://almedia.blob.core.windows.net/audio/56yQW8KfaD8.mp3": {
    "guid": "56yQW8KfaD8",
    "duration": 1931,
    "type": "audio/mpeg",
    "size": 30882102
  },
  "https://almedia.blob.core.windows.net/audio/sjbkeQM5Nj4.mp3": {
    "guid": "sjbkeQM5Nj4",
    "duration": 1581,
    "type": "audio/mpeg",
    "size": 25284792
  },
  "https://almedia.blob.core.windows.net/audio/Ray-InPSwaE.mp3": {
    "guid": "Ray-InPSwaE",
    "duration": 1357,
    "type": "audio/mpeg",
    "size": 21712913
  },
  "https://almedia.blob.core.windows.net/audio/3ubTTAthaE4.mp3": {
    "guid": "3ubTTAthaE4",
    "duration": 1333,
    "type": "audio/mpeg",
    "size": 21320032
  },
  "https://almedia.blob.core.windows.net/audio/yoZeKK01JWg.mp3": {
    "guid": "yoZeKK01JWg",
    "duration": 1162,
    "type": "audio/mpeg",
    "size": 18581563
  },
  "https://almedia.blob.core.windows.net/audio/9rGYjqo_SnE.mp3": {
    "guid": "9rGYjqo_SnE",
    "duration": 1499,
    "type": "audio/mpeg",
    "size": 23978670
  },
  "https://almedia.blob.core.windows.net/audio/0UvbNmiYXjc.mp3": {
    "guid": "0UvbNmiYXjc",
    "duration": 1287,
    "type": "audio/mpeg",
    "size": 20591111
  },
  "https://almedia.blob.core.windows.net/audio/duOue8741AM.mp3": {
    "guid": "duOue8741AM",
    "duration": 1343,
    "type": "audio/mpeg",
    "size": 21480528
  },
  "https://almedia.blob.core.windows.net/audio/Z4utyn60N1I.mp3": {
    "guid": "Z4utyn60N1I",
    "duration": 1255,
    "type": "audio/mpeg",
    "size": 20079111
  },
  "https://almedia.blob.core.windows.net/audio/OJjmZpttAGk.mp3": {
    "guid": "OJjmZpttAGk",
    "duration": 1589,
    "type": "audio/mpeg",
    "size": 25412688
  },
  "https://almedia.blob.core.windows.net/audio/YpPXhHvShd8.mp3": {
    "guid": "YpPXhHvShd8",
    "duration": 1247,
    "type": "audio/mpeg",
    "size": 19951215
  },
  "https://almedia.blob.core.windows.net/audio/a16RStwWTE8.mp3": {
    "guid": "a16RStwWTE8",
    "duration": 941,
    "type": "audio/mpeg",
    "size": 15050226
  },
  "https://almedia.blob.core.windows.net/audio/FEcH1Xsk7Ik.mp3": {
    "guid": "FEcH1Xsk7Ik",
    "duration": 1264,
    "type": "audio/mpeg",
    "size": 20222889
  },
  "https://almedia.blob.core.windows.net/audio/VSlkb6xZIyo.mp3": {
    "guid": "VSlkb6xZIyo",
    "duration": 2089,
    "type": "audio/mpeg",
    "size": 33420786
  },
  "https://almedia.blob.core.windows.net/audio/GspnMNDskGw.mp3": {
    "guid": "GspnMNDskGw",
    "duration": 2040,
    "type": "audio/mpeg",
    "size": 32628335
  },
  "https://almedia.blob.core.windows.net/audio/clVSrsLqYLs.mp3": {
    "guid": "clVSrsLqYLs",
    "duration": 2011,
    "type": "audio/mpeg",
    "size": 32163565
  },
  "https://almedia.blob.core.windows.net/audio/wehoyzBmkDU.mp3": {
    "guid": "wehoyzBmkDU",
    "duration": 1092,
    "type": "audio/mpeg",
    "size": 17460178
  },
  "https://almedia.blob.core.windows.net/audio/Rw1evvsIVuc.mp3": {
    "guid": "Rw1evvsIVuc",
    "duration": 1979,
    "type": "audio/mpeg",
    "size": 31651147
  },
  "https://almedia.blob.core.windows.net/audio/zFq444AnJ6w.mp3": {
    "guid": "zFq444AnJ6w",
    "duration": 2098,
    "type": "audio/mpeg",
    "size": 33557041
  },
  "https://almedia.blob.core.windows.net/audio/M6tOoD7q1Do.mp3": {
    "guid": "M6tOoD7q1Do",
    "duration": 1606,
    "type": "audio/mpeg",
    "size": 25684779
  },
  "https://almedia.blob.core.windows.net/audio/DW-HULB5hLc.mp3": {
    "guid": "DW-HULB5hLc",
    "duration": 3425,
    "type": "audio/mpeg",
    "size": 54793965
  },
  "https://almedia.blob.core.windows.net/audio/QxRXkEsYQPY.mp3": {
    "guid": "QxRXkEsYQPY",
    "duration": 3063,
    "type": "audio/mpeg",
    "size": 49004394
  },
  "https://almedia.blob.core.windows.net/audio/pg1C7b5sCrY.mp3": {
    "guid": "pg1C7b5sCrY",
    "duration": 1680,
    "type": "audio/mpeg",
    "size": 26870112
  },
  "https://almedia.blob.core.windows.net/audio/Gka-D-BJfY0.mp3": {
    "guid": "Gka-D-BJfY0",
    "duration": 1511,
    "type": "audio/mpeg",
    "size": 24170931
  },
  "https://almedia.blob.core.windows.net/audio/PBswH7yd8UM.mp3": {
    "guid": "PBswH7yd8UM",
    "duration": 1181,
    "type": "audio/mpeg",
    "size": 18893778
  },
  "https://almedia.blob.core.windows.net/audio/GnRigWlP3bo.mp3": {
    "guid": "GnRigWlP3bo",
    "duration": 1289,
    "type": "audio/mpeg",
    "size": 20623294
  },
  "https://almedia.blob.core.windows.net/audio/MjFx-Nsbeyw.mp3": {
    "guid": "MjFx-Nsbeyw",
    "duration": 1295,
    "type": "audio/mpeg",
    "size": 20711483
  },
  "https://almedia.blob.core.windows.net/audio/YOTH39FS2zM.mp3": {
    "guid": "YOTH39FS2zM",
    "duration": 1870,
    "type": "audio/mpeg",
    "size": 29913272
  },
  "https://almedia.blob.core.windows.net/audio/dh4BTuyi5ik.mp3": {
    "guid": "dh4BTuyi5ik",
    "duration": 2093,
    "type": "audio/mpeg",
    "size": 33484734
  },
  "https://almedia.blob.core.windows.net/audio/l_fhBcUGP5M.mp3": {
    "guid": "l_fhBcUGP5M",
    "duration": 1850,
    "type": "audio/mpeg",
    "size": 29588100
  },
  "https://almedia.blob.core.windows.net/audio/FbrbSoB2I7A.mp3": {
    "guid": "FbrbSoB2I7A",
    "duration": 2609,
    "type": "audio/mpeg",
    "size": 41731486
  },
  "https://almedia.blob.core.windows.net/audio/M0Svr2Lp2Vg.mp3": {
    "guid": "M0Svr2Lp2Vg",
    "duration": 2910,
    "type": "audio/mpeg",
    "size": 46553481
  },
  "https://almedia.blob.core.windows.net/audio/RnV-dsqFJbg.mp3": {
    "guid": "RnV-dsqFJbg",
    "duration": 2229,
    "type": "audio/mpeg",
    "size": 35654360
  },
  "https://almedia.blob.core.windows.net/audio/JJ1rLyKajdg.mp3": {
    "guid": "JJ1rLyKajdg",
    "duration": 3196,
    "type": "audio/mpeg",
    "size": 51125955
  },
  "https://almedia.blob.core.windows.net/audio/MRpbQcce2cg.mp3": {
    "guid": "MRpbQcce2cg",
    "duration": 3175,
    "type": "audio/mpeg",
    "size": 50797439
  },
  "https://almedia.blob.core.windows.net/audio/w04cipt6oEQ.mp3": {
    "guid": "w04cipt6oEQ",
    "duration": 2585,
    "type": "audio/mpeg",
    "size": 41347800
  },
  "https://almedia.blob.core.windows.net/audio/CuN2YrMXs6o.mp3": {
    "guid": "CuN2YrMXs6o",
    "duration": 1989,
    "type": "audio/mpeg",
    "size": 31810389
  },
  "https://almedia.blob.core.windows.net/audio/4B5p-8M2MDY.mp3": {
    "guid": "4B5p-8M2MDY",
    "duration": 1325,
    "type": "audio/mpeg",
    "size": 21200077
  },
  "https://almedia.blob.core.windows.net/audio/fX_ogqPdNtg.mp3": {
    "guid": "fX_ogqPdNtg",
    "duration": 1767,
    "type": "audio/mpeg",
    "size": 28271111
  },
  "https://almedia.blob.core.windows.net/audio/p6wERaJ2Tto.mp3": {
    "guid": "p6wERaJ2Tto",
    "duration": 2090,
    "type": "audio/mpeg",
    "size": 33435832
  },
  "https://almedia.blob.core.windows.net/audio/VK7m8My5Bmw.mp3": {
    "guid": "VK7m8My5Bmw",
    "duration": 2221,
    "type": "audio/mpeg",
    "size": 35533987
  },
  "https://almedia.blob.core.windows.net/audio/5umwqerdMWo.mp3": {
    "guid": "5umwqerdMWo",
    "duration": 1272,
    "type": "audio/mpeg",
    "size": 20340335
  },
  "https://almedia.blob.core.windows.net/audio/9JpctINAbAE.mp3": {
    "guid": "9JpctINAbAE",
    "duration": 1561,
    "type": "audio/mpeg",
    "size": 24961710
  },
  "https://almedia.blob.core.windows.net/audio/NjcwhN108j4.mp3": {
    "guid": "NjcwhN108j4",
    "duration": 1417,
    "type": "audio/mpeg",
    "size": 22668368
  },
  "https://almedia.blob.core.windows.net/audio/3LYt82kK794.mp3": {
    "guid": "3LYt82kK794",
    "duration": 1944,
    "type": "audio/mpeg",
    "size": 31100276
  },
  "https://almedia.blob.core.windows.net/audio/V1edbeK2MSU.mp3": {
    "guid": "V1edbeK2MSU",
    "duration": 2218,
    "type": "audio/mpeg",
    "size": 26608412
  },
  "https://almedia.blob.core.windows.net/audio/5Uc55EjyrCc.mp3": {
    "guid": "5Uc55EjyrCc",
    "duration": 2368,
    "type": "audio/mpeg",
    "size": 37886680
  },
  "https://almedia.blob.core.windows.net/audio/r3SbtC_TsJ4.mp3": {
    "guid": "r3SbtC_TsJ4",
    "duration": 2047,
    "type": "audio/mpeg",
    "size": 32744528
  },
  "https://almedia.blob.core.windows.net/audio/iiksKR3wFYo.mp3": {
    "guid": "iiksKR3wFYo",
    "duration": 2280,
    "type": "audio/mpeg",
    "size": 36470216
  },
  "https://almedia.blob.core.windows.net/audio/66lNaHAg2gs.mp3": {
    "guid": "66lNaHAg2gs",
    "duration": 1672,
    "type": "audio/mpeg",
    "size": 26750157
  },
  "https://almedia.blob.core.windows.net/audio/opF7XVZqJYw.mp3": {
    "guid": "opF7XVZqJYw",
    "duration": 1866,
    "type": "audio/mpeg",
    "size": 29850578
  },
  "https://almedia.blob.core.windows.net/audio/Vda7aqvdf1c.mp3": {
    "guid": "Vda7aqvdf1c",
    "duration": 1580,
    "type": "audio/mpeg",
    "size": 25268910
  },
  "https://almedia.blob.core.windows.net/audio/SAJmMacyhPI.mp3": {
    "guid": "SAJmMacyhPI",
    "duration": 1689,
    "type": "audio/mpeg",
    "size": 27011800
  },
  "https://almedia.blob.core.windows.net/audio/MCA5Rt9xt00.mp3": {
    "guid": "MCA5Rt9xt00",
    "duration": 1778,
    "type": "audio/mpeg",
    "size": 28442056
  },
  "https://almedia.blob.core.windows.net/audio/NgFb0aOsPNU.mp3": {
    "guid": "NgFb0aOsPNU",
    "duration": 3205,
    "type": "audio/mpeg",
    "size": 51277256
  },
  "https://almedia.blob.core.windows.net/audio/8c-_qQLVsz8.mp3": {
    "guid": "8c-_qQLVsz8",
    "duration": 2439,
    "type": "audio/mpeg",
    "size": 39018095
  },
  "https://almedia.blob.core.windows.net/audio/i-WSuG6aXJg.mp3": {
    "guid": "i-WSuG6aXJg",
    "duration": 2288,
    "type": "audio/mpeg",
    "size": 36607307
  },
  "https://almedia.blob.core.windows.net/audio/Zyza4h1AvHc.mp3": {
    "guid": "Zyza4h1AvHc",
    "duration": 1742,
    "type": "audio/mpeg",
    "size": 27866944
  },
  "https://almedia.blob.core.windows.net/audio/Sd0i55ikM_Q.mp3": {
    "guid": "Sd0i55ikM_Q",
    "duration": 2703,
    "type": "audio/mpeg",
    "size": 43241573
  },
  "https://almedia.blob.core.windows.net/audio/TrJkuOuha1U.mp3": {
    "guid": "TrJkuOuha1U",
    "duration": 3325,
    "type": "audio/mpeg",
    "size": 53190673
  },
  "https://almedia.blob.core.windows.net/audio/nIbXF--edx0.mp3": {
    "guid": "nIbXF--edx0",
    "duration": 1771,
    "type": "audio/mpeg",
    "size": 21249989
  },
  "https://almedia.blob.core.windows.net/audio/IWGVfVN7rKA.mp3": {
    "guid": "IWGVfVN7rKA",
    "duration": 1707,
    "type": "audio/mpeg",
    "size": 20484809
  },
  "https://almedia.blob.core.windows.net/audio/0XaIqeZVOh8.mp3": {
    "guid": "0XaIqeZVOh8",
    "duration": 1630,
    "type": "audio/mpeg",
    "size": 19562571
  },
  "https://almedia.blob.core.windows.net/audio/-dULR0idhG0.mp3": {
    "guid": "-dULR0idhG0",
    "duration": 2541,
    "type": "audio/mpeg",
    "size": 30490464
  },
  "https://almedia.blob.core.windows.net/audio/ZWJVvsNzA8Y.mp3": {
    "guid": "ZWJVvsNzA8Y",
    "duration": 1491,
    "type": "audio/mpeg",
    "size": 17888975
  }
}